{
    "MAC": {},
    "ERU": {},
    "MEA": {},
    "drop_coordinates": {
        "1": {
            "vehicle": "MAC",
            "latitude": 35.12345,
            "longtitude": 44.12345
        },
        "2": {
            "vehicle": "ERU",
            "latitude": 19.12345,
            "longtitude": 21.12345
        }
    },
    "search_area_coordinates": {
        "1": {
            "SearchArea": [
                {
                    "longtitude": 99.12345,
                    "latitude": 88.12345
                },
                {
                    "longtitude": 99.12345,
                    "latitude": 88.12345
                },
                {
                    "longtitude": 99.12345,
                    "latitude": 88.12345
                }
            ]
        }
    },
    "evacuation_coordinates": {
        "1": {
            "vehicle": "MEA",
            "latitude": 46,
            "longtitude": 52.2
        },
        "2": {
            "vehicle": "ERU",
            "latitude": 46,
            "longtitude": 52.2
        }
    }
}
